movin_calc/__init__.py
movincalc-0.1.dist-info/LICENSE.txt
movincalc-0.1.dist-info/METADATA
movincalc-0.1.dist-info/WHEEL
movincalc-0.1.dist-info/top_level.txt
movincalc-0.1.dist-info/RECORD
