Metadata-Version: 2.1
Name: movincalc
Version: 0.1
Summary: Basic calculator
Author: Movin Fernandes
Author-email: movin.fernandes@hotmail.com
Classifier: Programming Language :: Python :: 3
Classifier: License :: OSI Approved :: MIT License
Classifier: Operating System :: OS Independent
License-File: LICENSE.txt
